decentralizedroutines/RoutineScheduler.py
decentralizedroutines/__init__.py
decentralizedroutines/defaults.py
decentralizedroutines/master.py
decentralizedroutines/runroutines.py
decentralizedroutines/update_version_requirements.py
decentralizedroutines/worker.py
decentralizedroutines/worker_lib.py
decentralizedroutines-3.0.3.dist-info/LICENSE
decentralizedroutines-3.0.3.dist-info/METADATA
decentralizedroutines-3.0.3.dist-info/WHEEL
decentralizedroutines-3.0.3.dist-info/top_level.txt
decentralizedroutines-3.0.3.dist-info/RECORD
