Metadata-Version: 2.1
Name: decentralizedroutines
Version: 3.0.3
Summary: Master/Worker implementation of decentralized git published routines and kinesis worker pool
Home-page: https://github.com/jcarlitooliveira/DecentralizedRoutines
Author: Jose Carlito de Oliveira Filho
Author-email: jcarlitooliveira@gmail.com
Project-URL: Bug Tracker, https://github.com/jcarlitooliveira/DecentralizedRoutines/issues
Classifier: Programming Language :: Python :: 3
Classifier: License :: OSI Approved :: MIT License
Classifier: Operating System :: OS Independent
Requires-Python: >=3.9
License-File: LICENSE
Requires-Dist: shareddata (==3.0.3)
Requires-Dist: psutil (==5.9.5)
Requires-Dist: tzlocal (==4.1)
